openapi_client/__init__.py
openapi_client/api/__init__.py
openapi_client/api/apiv1_api.py
openapi_client/api/exec_apiv1_api.py
openapi_client/api/ssoapiv1_api.py
openapi_client/api_client.py
openapi_client/configuration.py
openapi_client/exceptions.py
openapi_client/models/__init__.py
openapi_client/models/account_get_my_workload_list_response.py
openapi_client/models/account_invitation_token_validate_response.py
openapi_client/models/account_set_default_organiztion_api_input.py
openapi_client/models/account_sign_in_cli_check_response.py
openapi_client/models/account_sign_in_cli_token_response.py
openapi_client/models/account_ssh_key_list_response.py
openapi_client/models/add_git_ssh_key_api_input.py
openapi_client/models/artifact_artifact_create_artifact_locator_response.py
openapi_client/models/artifact_create_artifact_locator_api_input.py
openapi_client/models/artifact_persistent_artifact_list_response.py
openapi_client/models/auto_top_up_config_update_api_input.py
openapi_client/models/billing_customer_portal_response.py
openapi_client/models/billing_manual_top_up_response.py
openapi_client/models/bit_bucket_authorize_api_input.py
openapi_client/models/change_password_api_input.py
openapi_client/models/cli_experiment_freeze_dataset_version_api_input.py
openapi_client/models/cli_workspace_backup_create_api_input.py
openapi_client/models/clientconfig_frontend_config_response.py
openapi_client/models/cluster_access_delete_api_input.py
openapi_client/models/cluster_access_upsert_api_input.py
openapi_client/models/cluster_cert_upload_api_input.py
openapi_client/models/cluster_cluster_access_list_response.py
openapi_client/models/cluster_cluster_cert_list_response.py
openapi_client/models/cluster_cluster_event_list_response.py
openapi_client/models/cluster_cluster_ingress_class_list_response.py
openapi_client/models/cluster_cluster_list_response.py
openapi_client/models/cluster_cluster_node_cordon_response.py
vessl-0.1.198.dist-info/LICENSE
vessl-0.1.198.dist-info/METADATA
vessl-0.1.198.dist-info/WHEEL
vessl-0.1.198.dist-info/entry_points.txt
vessl-0.1.198.dist-info/RECORD
