Metadata-Version: 2.3
Name: vessl
Version: 0.1.198
Summary: SDK and CLI for VESSL
License: MIT
Author: VESSL AI Dev Team
Author-email: contact@vessl.ai
Requires-Python: >=3.9,<3.13
Classifier: License :: OSI Approved :: MIT License
Classifier: Programming Language :: Python :: 3
Classifier: Programming Language :: Python :: 3.9
Classifier: Programming Language :: Python :: 3.10
Classifier: Programming Language :: Python :: 3.11
Classifier: Programming Language :: Python :: 3.12
Provides-Extra: media
Requires-Dist: boto3 (>=1.18.9)
Requires-Dist: brotli (>=1.1.0,<2.0.0)
Requires-Dist: click (>=8.0.1)
Requires-Dist: cloudpickle (>=1.6.0,<4.0.0)
Requires-Dist: docker (>=6.0.1)
Requires-Dist: google-auth (>=2.28.2,<3.0.0)
Requires-Dist: google-cloud-storage (>=2.15.0,<3.0.0)
Requires-Dist: humanfriendly (>=10.0,<11.0)
Requires-Dist: inquirer (>=3.1.3)
Requires-Dist: kubernetes (>=28.1.0)
Requires-Dist: packaging (>=15.0)
Requires-Dist: paramiko (>=3.4.0,<4.0.0)
Requires-Dist: prometheus-client (>=0.20.0,<0.21.0)
Requires-Dist: pydantic (>=2.8.2,<3,!=2.9.0)
Requires-Dist: python-dotenv (>=1.0.0,<2.0.0)
Requires-Dist: pyyaml (>=6.0.1,<7.0.0)
Requires-Dist: requests (>=2.26.0,<3.0.0)
Requires-Dist: requests-futures (>=1.0.0)
Requires-Dist: sentry-sdk (>=1.3.1)
Requires-Dist: six (>=1.16.0,<2.0.0)
Requires-Dist: sshpubkeys (>=3.3.1,<4.0.0)
Requires-Dist: tabulate (>=0.9.0,<0.10.0)
Requires-Dist: terminaltables (>=3.1.0)
Requires-Dist: toml (>=0.10.1,<0.11.0)
Requires-Dist: tqdm (>=4.61.2,<5.0.0)
Requires-Dist: uvicorn (>=0.16.0)
Requires-Dist: watchdog (>=3.0.0,<4.0.0)
Project-URL: Homepage, https://vessl.ai/
